coffee/coffee.v
`timescale 1ns/1ps

module coffee(
	input RST, CLK, C_IN, B_IN,
	output reg BAL, COFF
);

//posible states
	localparam  COUNTER = 2'b00,
			C_25 = 2'b01,
			C_50 = 2'b10;
			
// 2 bit regioster for store the states
	reg [1:0] STATE;
	
	always @(posedge CLK)
		begin
			if(RST==1)
				STATE <= COUNTER;
				
			else
				begin
					case(STATE)
					//first case
					COUNTER:begin
						COFF <= 0;
						BAL <= 0;
						
						if(C_IN ==1)
							STATE <= C_25;
						
						else if (B_IN == 1) 
							begin
								STATE <= COUNTER;
								BAL <= 1;
								COFF <= 1;
							end
						
						else
							STATE <= COUNTER;
					end
					
					// second case
					C_25 : begin
						COFF <= 0;
						BAL <= 0;
						
						if(C_IN ==1)
							STATE <= C_50; 
							
						else
							STATE <= C_25;
						
					end
					
					//third case
					C_50 : begin
						COFF <= 0;
						BAL <= 0;
						
						if(C_IN ==1)
						begin
							STATE <= COUNTER;
							COFF <= 1;
						end
							
						else
							STATE <= C_50;
						
					end
					
					default:
						STATE <= COUNTER;
						
				endcase
			end
		end
endmodule

Coffee_Machine/coffee_tb.v
// test bench for coffee vendor

`timescale 1ns / 1ps

module coffee_tb();

	reg clk , rst, c_in, b_in;
	wire coff, bal;
	
	//initiate module to test
	coffee ut(.CLK(clk), .RST(rst), .C_IN(c_in), .B_IN(b_in), .COFF(coff), .BAL(bal));
	
	always #5 clk = !clk;
	
	initial begin
	$dumpfile("coffee.vcd");
    $dumpvars();
	
	clk=0; rst=0; c_in=0; b_in=0;
	
	#5 rst = 0;
	#10 c_in = 1;
	#10 c_in = 0;
	#10 c_in = 1;
	#10 c_in = 1;
	#10 c_in = 0;
	#10 c_in = 1;
	#10 c_in = 1;
	#10 c_in = 1;
	#10 c_in = 0;
	
	#10 b_in = 1;
	#10 b_in = 0;
	#10 b_in = 1;
	#10 b_in = 1;
	#10 b_in = 0;
	
	#10 $finish;
	
	end
endmodule

Coffee_Machine/coffee.vcd
$date
	Wed Jul 31 18:13:48 2024
$end
$version
	Icarus Verilog
$end
$timescale
	1ps
$end
$scope module coffee_tb $end
$var wire 1 ! coff $end
$var wire 1 " bal $end
$var reg 1 # b_in $end
$var reg 1 $ c_in $end
$var reg 1 % clk $end
$var reg 1 & rst $end
$scope module ut $end
$var wire 1 # B_IN $end
$var wire 1 % CLK $end
$var wire 1 $ C_IN $end
$var wire 1 & RST $end
$var parameter 2 ' COUNTER $end
$var parameter 2 ( C_25 $end
$var parameter 2 ) C_50 $end
$var reg 1 " BAL $end
$var reg 1 ! COFF $end
$var reg 2 * STATE [1:0] $end
$upscope $end
$upscope $end
$enddefinitions $end
$comment Show the parameter values. $end
$dumpall
b10 )
b1 (
b0 '
$end
#0
$dumpvars
bx *
0&
0%
0$
0#
x"
x!
$end
#5000
b0 *
1%
#10000
0%
#15000
b1 *
0"
0!
1%
1$
#20000
0%
#25000
1%
0$
#30000
0%
#35000
b10 *
1%
1$
#40000
0%
#45000
1!
b0 *
1%
#50000
0%
#55000
0!
1%
0$
#60000
0%
#65000
b1 *
1%
1$
#70000
0%
#75000
b10 *
1%
#80000
0%
#85000
1!
b0 *
1%
#90000
0%
#95000
0!
1%
0$
#100000
0%
#105000
1!
1"
1%
1#
#110000
0%
#115000
0"
0!
1%
0#
#120000
0%
#125000
1!
1"
1%
1#
#130000
0%
#135000
1"
1!
1%
#140000
0%
#145000
0"
0!
1%
0#
