door_locking/push.v
`timescale 1ns / 1ps

module push(
	input CLK, RST, PRESS,
	output reg M_CW, M_ACW

);

	//defining states
	//state values are constatnts
	localparam D_Lock = 1'b0,
			   D_Unlock = 1'b1;
			   
	reg STATE;
	
	always @(posedge CLK)
		begin
		
			if(RST==1)
				STATE <= D_Lock;
				
			else
				begin
					case(STATE)
						D_Unlock:begin
							M_ACW <= 0;
							
							if(PRESS == 1)
								begin
									STATE <= D_Lock;
									M_CW <= 1;
								end
								
							else
								begin
									STATE <= D_Unlock;
									M_CW <= 0;
								end
						end
						
						D_Lock: begin
							M_CW <= 0;
							
							if (PRESS == 1)
								begin
									STATE <= D_Unlock;
									M_ACW <= 1;
								end
							else
								begin
									STATE <= D_Lock;
									M_ACW <= 0;
								end
						end
						
						default:
							STATE <= D_Lock;
						
				endcase
			end
		end
endmodule

door_locking/push_tb.v
// push button door control test bench

`timescale 1ns/ 1ps

module push_tb;
	reg clk,rst,press;
	wire m_cw,m_acw;
	
	push ut(.CLK(clk), .RST(rst), .PRESS(press), .M_CW(m_cw), .M_ACW(m_acw));
	
	always #5 clk =! clk;
	
	initial begin
	$dumpfile("push.vcd");
    $dumpvars();
	
	clk=0; rst=0; press=0;
	
	#10 rst = 0;
	#10 press = 1;
	#10 press = 0;
	#10 press = 0;
	#10 press = 1;
	#10 press = 0;
	#10 press = 1;
	#10 press = 1;
	#10 press = 0;
	#20 $finish;
	
	end
endmodule

Door_Lock/push.vcd
$date
	Sat Jul 27 19:50:32 2024
$end
$version
	Icarus Verilog
$end
$timescale
	1ps
$end
$scope module push_tb $end
$var wire 1 ! m_cw $end
$var wire 1 " m_acw $end
$var reg 1 # clk $end
$var reg 1 $ press $end
$var reg 1 % rst $end
$scope module ut $end
$var wire 1 # CLK $end
$var wire 1 $ PRESS $end
$var wire 1 % RST $end
$var parameter 1 & D_Lock $end
$var parameter 1 ' D_Unlock $end
$var reg 1 " M_ACW $end
$var reg 1 ! M_CW $end
$var reg 1 ( STATE $end
$upscope $end
$upscope $end
$enddefinitions $end
$comment Show the parameter values. $end
$dumpall
1'
0&
$end
#0
$dumpvars
x(
0%
0$
0#
x"
x!
$end
#5000
0(
1#
#10000
0#
#15000
0"
0!
1#
#20000
0#
1$
#25000
1"
1(
1#
#30000
0#
0$
#35000
0"
1#
#40000
0#
#45000
1#
#50000
0#
1$
#55000
1!
0(
1#
#60000
0#
0$
#65000
0!
1#
#70000
0#
1$
#75000
1"
1(
1#
#80000
0#
#85000
1!
0(
0"
1#
#90000
0#
0$
#95000
0!
1#
